siliconflow_mcp_server/__init__.py
siliconflow_mcp_server/server.py
siliconflow_mcp_server-0.3.6.dist-info/METADATA
siliconflow_mcp_server-0.3.6.dist-info/WHEEL
siliconflow_mcp_server-0.3.6.dist-info/entry_points.txt
siliconflow_mcp_server-0.3.6.dist-info/top_level.txt
siliconflow_mcp_server-0.3.6.dist-info/RECORD
