Metadata-Version: 2.2
Name: siliconflow_mcp_server
Version: 0.3.6
Summary: MCP Server for siliconflow
Author-email: xu <xhjxhj001@gmail.com>
Requires-Python: >=3.10
Requires-Dist: requests>=2.32.3
Requires-Dist: httpx>=0.28.1
Requires-Dist: mcp[cli]>=1.3.0
